neverlose/__init__.py
neverlose/client.py
neverlose/enums/__init__.py
neverlose/enums/event_type.py
neverlose/eventbus.py
neverlose/exceptions/__init__.py
neverlose/exceptions/api_exception.py
neverlose/handlers/__init__.py
neverlose/methods/__init__.py
neverlose/methods/market.py
neverlose/models/__init__.py
neverlose/models/base/__init__.py
neverlose/models/base/event.py
neverlose/models/base/response.py
neverlose/models/events/__init__.py
neverlose/models/events/balance_transfer.py
neverlose/models/events/item_purchase.py
neverlose/models/responses/__init__.py
neverlose/models/responses/failed.py
neverlose/models/responses/ok.py
neverlose/requests.py
neverlose/scaffold.py
neverlose/types.py
neverlose/utils/__init__.py
neverlose/utils/signature.py
neverlose-1.0.2.dist-info/LICENSE.md
neverlose-1.0.2.dist-info/WHEEL
neverlose-1.0.2.dist-info/METADATA
neverlose-1.0.2.dist-info/RECORD
