Metadata-Version: 2.1
Name: neverlose
Version: 1.0.2
Summary: Neverlose web api wrapper
Author: es3n1n
Requires-Python: >=3.7,<4.0
Classifier: Programming Language :: Python :: 3
Classifier: Programming Language :: Python :: 3.7
Classifier: Programming Language :: Python :: 3.8
Classifier: Programming Language :: Python :: 3.9
Requires-Dist: fastapi (>=0.63.0,<0.64.0)
Requires-Dist: pydantic (>=1.8.1,<2.0.0)
Requires-Dist: requests (>=2.25.1,<3.0.0)
Requires-Dist: uvicorn (>=0.13.4,<0.14.0)
